Metadata-Version: 2.1
Name: simple-env
Version: 0.4.0
Summary: Super Simple Processing of Environmental Variables
Home-page: https://github.com/DanielJDufour/simple-env
Author: Daniel J. Dufour
Author-email: daniel.j.dufour@gmail.com
License: UNKNOWN
Download-URL: https://github.com/DanielJDufour/simple-env/tarball/download
Keywords: env,environment,python,variables
Platform: UNKNOWN
Classifier: Development Status :: 3 - Alpha
Classifier: Programming Language :: Python :: 3
Classifier: License :: CC0 1.0 Universal (CC0 1.0) Public Domain Dedication
Classifier: Operating System :: OS Independent
